{
  "_fv": 79,
  "_type": "achievement",
  "definition": {
    "achievementName": "Post Mortem",
    "achievementDescription": "Reaparece",
    "achievementIcon": {
      "value": "Items.SKULL#0"
    },
    "background": "Default",
    "disableDisplay": true,
    "showPopup": true,
    "announceToChat": true,
    "hideIfNotCompleted": true,
    "rewardLoot": [],
    "rewardRecipes": [],
    "rewardXP": 0,
    "achievementType": "task",
    "parent": {
      "value": "No parent: root"
    },
    "triggerxml": "<xml xmlns=\"https://developers.google.com/blockly/xml\"><block type=\"advancement_trigger\" deletable=\"false\" x=\"108\" y=\"96\"><next><block type=\"custom_trigger\"></block></next></block></xml>"
  }
}